plugin_viperlog_console/__init__.py
plugin_viperlog_console/console_formatter.py
plugin_viperlog_console/console_processor.py
plugin_viperlog_console/console_template.py
viperlog_console_plugin-0.2.102.dist-info/METADATA
viperlog_console_plugin-0.2.102.dist-info/WHEEL
viperlog_console_plugin-0.2.102.dist-info/top_level.txt
viperlog_console_plugin-0.2.102.dist-info/RECORD
