Metadata-Version: 2.4
Name: viperlog-console-plugin
Version: 0.2.102
Summary: Console handler for ViperLog
License-Expression: MIT
Requires-Python: >=3.12
Requires-Dist: viperlog>=0.2.102
Requires-Dist: rich>=14.1.0
